mutornadomon/__init__.py
mutornadomon/config.py
mutornadomon/monitor.py
mutornadomon/net.py
mutornadomon/utils.py
mutornadomon/collectors/__init__.py
mutornadomon/collectors/ioloop_util.py
mutornadomon/collectors/web.py
mutornadomon/external_interfaces/__init__.py
mutornadomon/external_interfaces/http_endpoints.py
mutornadomon/external_interfaces/publish.py
mutornadomon-0.4.4.dist-info/DESCRIPTION.rst
mutornadomon-0.4.4.dist-info/METADATA
mutornadomon-0.4.4.dist-info/RECORD
mutornadomon-0.4.4.dist-info/WHEEL
mutornadomon-0.4.4.dist-info/metadata.json
mutornadomon-0.4.4.dist-info/top_level.txt
