Metadata-Version: 2.0
Name: mutornadomon
Version: 0.4.4
Summary: Library of standard monitoring hooks for the Tornado framework
Home-page: https://github.com/uber/mutornadomon
Author: Uber Technologies, Inc.
Author-email: dev@uber.com
License: MIT
Keywords: monitoring,tornado
Platform: UNKNOWN
Classifier: Development Status :: 3 - Alpha
Classifier: Environment :: Web Environment
Classifier: Programming Language :: Python
Classifier: Programming Language :: Python :: 2.6
Classifier: Programming Language :: Python :: 2.7
Classifier: Programming Language :: Python :: 3.3
Classifier: Programming Language :: Python :: 3.4
Classifier: Intended Audience :: System Administrators
Classifier: Operating System :: OS Independent
Classifier: License :: OSI Approved :: MIT License
Classifier: Topic :: System :: Monitoring
Classifier: Topic :: System :: Systems Administration
Requires-Dist: ipcalc
Requires-Dist: mock
Requires-Dist: psutil
Requires-Dist: six
Requires-Dist: tornado
